GWASkit/__init__.py
GWASkit-0.0.0.dist-info/LICENSE
GWASkit-0.0.0.dist-info/METADATA
GWASkit-0.0.0.dist-info/WHEEL
GWASkit-0.0.0.dist-info/top_level.txt
GWASkit-0.0.0.dist-info/RECORD
